osm_to_xodr/__init__.py
osm_to_xodr/cli.py
osm_to_xodr/config.py
osm_to_xodr/converter.py
osm_to_xodr/netconvert.py
osm_to_xodr/postprocess.py
osm_to_xodr/py.typed
osm_to_xodr-0.3.0.dist-info/METADATA
osm_to_xodr-0.3.0.dist-info/WHEEL
osm_to_xodr-0.3.0.dist-info/entry_points.txt
osm_to_xodr-0.3.0.dist-info/licenses/LICENSE
osm_to_xodr-0.3.0.dist-info/RECORD
