Metadata-Version: 2.4
Name: osm-to-xodr
Version: 0.3.0
Summary: Convert OpenStreetMap (.osm) files to OpenDRIVE (.xodr) using SUMO netconvert with sane defaults
Project-URL: Homepage, https://github.com/RISE-Dependable-Transport-Systems/osm-to-xodr
Project-URL: Repository, https://github.com/RISE-Dependable-Transport-Systems/osm-to-xodr
Project-URL: Issues, https://github.com/RISE-Dependable-Transport-Systems/osm-to-xodr/issues
Project-URL: Changelog, https://github.com/RISE-Dependable-Transport-Systems/osm-to-xodr/blob/main/CHANGELOG.md
Author-email: Karl Lundgren <k.github@lundgrens.net>
License: MIT
License-File: LICENSE
Keywords: carla,netconvert,opendrive,osm,simulation,sumo,xodr
Classifier: Development Status :: 4 - Beta
Classifier: Environment :: Console
Classifier: Intended Audience :: Developers
Classifier: Intended Audience :: Science/Research
Classifier: License :: OSI Approved :: MIT License
Classifier: Operating System :: OS Independent
Classifier: Programming Language :: Python :: 3
Classifier: Programming Language :: Python :: 3.11
Classifier: Programming Language :: Python :: 3.12
Classifier: Topic :: Scientific/Engineering :: GIS
Classifier: Topic :: Software Development :: Libraries :: Python Modules
Classifier: Typing :: Typed
Requires-Python: >=3.11
Requires-Dist: loguru>=0.7.0
Requires-Dist: pydantic-settings>=2.0.0
Requires-Dist: pydantic>=2.0.0
Requires-Dist: rich>=13.0.0
Requires-Dist: typer>=0.15.0
Requires-Dist: utm>=0.8.1
